GpioEmu.v
module GpioEmu(n_reset, saddress[15:0], srd, swr, sdata_in[31:0], sdata_out[31:0], gpio_in[31:0], gpio_latch, gpio_out[31:0], clk, gpio_in_s_insp[31:0]);

input n_reset;
input [15:0] saddress;
input srd;
input swr;
input [31:0] sdata_in;
input [31:0] gpio_in;
input gpio_latch;
input clk;

output[31:0] sdata_out;
output [31:0] gpio_out;
output [31:0] gpio_in_s_insp;

reg [31:0] gpio_in_s;
reg [31:0] gpio_out_s;
reg [31:0] sdata_out_s;



//Reset
always@(negedge n_reset) begin
    sdata_out_s <= 0;
    gpio_out_s <= 0;
    gpio_in_s <= 0;
end

// odczyt z portu GPIO
always@(posedge gpio_latch) begin
    gpio_in_s <= gpio_in;
end

// odczyt na gpio

wire [11:0] cut_address;
assign cut_address = {saddress[15:8], saddress[3:0]};

always@(posedge srd) begin
    if(cut_address == 12'h6b0)
        //sdata_out_s <= gpio_in_s[3:0] << 8;
        sdata_out_s <= (gpio_in_s & 32'h0f) << 8;
    else if (cut_address == 12'hdb0) 
        sdata_out_s <= (gpio_in_s & 32'h0f) << 20;
    // else 
    //     sdata_out_s <= 0;
end


always@(posedge swr) begin
    if(cut_address == 12'h6b0)
        gpio_out_s[3:0] <= sdata_in[11:8];  
    else if (cut_address == 12'hdb0) 
        gpio_out_s[7:4] <= sdata_in[23:20];  
    // else 
    //     gpio_out_s <= gpio_out;
end

assign sdata_out = sdata_out_s;
assign gpio_out = gpio_out_s;
assign gpio_in_s_insp = gpio_in_s;


endmodule

GpioEmu_tb.v
`timescale 1 ns /10 ps

module GpioEmu_tb;

	reg  n_reset = 1;
	reg[15:0] saddress = 0;
	reg[31:0] sdata_in = 0;
	reg[31:0] gpio_in = 0;
	reg gpio_latch = 0;
	reg clk= 0;
	reg srd = 0;
	reg swr = 0;

	wire[31:0] gpio_out_test;
	wire[31:0] sdata_out_test;
	wire[31:0] gpio_in_s_insp_test;

	initial begin
		$dumpfile("GpioEmu.vcd");
		$dumpvars(0,GpioEmu_tb);
	end
	
	always
		#1 clk= ~clk;

    initial begin 

        //reset
        # 5 n_reset = 0;
        # 5 n_reset = 1;

        //zapis 1 oś
        #5 saddress= 16'h6ba0;
		#5 sdata_in = 32'h123fffaa;
		#5 swr= 1;
		#5 swr= 0;

        //zapis 2 oś
        #5 saddress= 16'hdb10;
		#5 sdata_in = 32'h123fffaa;
		#5 swr= 1;
		#5 swr= 0;

        //zły zapis
        #5 saddress= 16'hffff;
		#5 sdata_in = 32'h123fffaa;
		#5 swr= 1;
		#5 swr= 0;

        //reset
        # 5 n_reset = 0;
        # 5 n_reset = 1;

        //odczyt z osi 1
		#5 gpio_in = 32'h123fffaa;
		#5 gpio_latch = 1;
		#5 gpio_latch = 0;
		#5 saddress= 16'h6ba0;
		#5 srd= 1;
		#5 srd= 0;
		
		//odczyt z osi 2
		#5 gpio_in = 32'h123fffaa;
		#5 gpio_latch = 1;
		#5 gpio_latch = 0;
		#5 saddress= 16'hdb10;;
		#5 srd= 1;
		#5 srd= 0;

		//odczyt ze złego adresu
		#5 gpio_in = 32'h123fffaa;
		#5 gpio_latch = 1;
		#5 gpio_latch = 0;
		#5 saddress= 16'hffff;
		#5 srd= 1;
		#5 srd= 0;

		//reset
		#5 n_reset = 0;
		#5 n_reset = 1;

		#300 srd= 1;
		#1500 $finish;

	end
	GpioEmu test1(n_reset, saddress, srd, swr, sdata_in, sdata_out_test, gpio_in, gpio_latch, gpio_out_test, clk, gpio_in_s_insp_test);
endmodule

GpioEmu.vcd
$date
	Tue Apr 26 18:04:44 2022
$end
$version
	Icarus Verilog
$end
$timescale
	10ps
$end
$scope module GpioEmu_tb $end
$var wire 32 ! sdata_out_test [31:0] $end
$var wire 32 " gpio_out_test [31:0] $end
$var wire 32 # gpio_in_s_insp_test [31:0] $end
$var reg 1 $ clk $end
$var reg 32 % gpio_in [31:0] $end
$var reg 1 & gpio_latch $end
$var reg 1 ' n_reset $end
$var reg 16 ( saddress [15:0] $end
$var reg 32 ) sdata_in [31:0] $end
$var reg 1 * srd $end
$var reg 1 + swr $end
$scope module test1 $end
$var wire 1 $ clk $end
$var wire 32 , gpio_in [31:0] $end
$var wire 32 - gpio_in_s_insp [31:0] $end
$var wire 1 & gpio_latch $end
$var wire 32 . gpio_out [31:0] $end
$var wire 1 ' n_reset $end
$var wire 16 / saddress [15:0] $end
$var wire 32 0 sdata_in [31:0] $end
$var wire 32 1 sdata_out [31:0] $end
$var wire 1 * srd $end
$var wire 1 + swr $end
$var wire 12 2 cut_address [11:0] $end
$var reg 32 3 gpio_in_s [31:0] $end
$var reg 32 4 gpio_out_s [31:0] $end
$var reg 32 5 sdata_out_s [31:0] $end
$upscope $end
$upscope $end
$enddefinitions $end
#0
$dumpvars
bx 5
bx 4
bx 3
b0 2
bx 1
b0 0
b0 /
bx .
bx -
b0 ,
0+
0*
b0 )
b0 (
1'
0&
b0 %
0$
bx #
bx "
bx !
$end
#100
1$
#200
0$
#300
1$
#400
0$
#500
b0 #
b0 -
b0 3
b0 "
b0 .
b0 4
b0 !
b0 1
b0 5
1$
0'
#600
0$
#700
1$
#800
0$
#900
1$
#1000
0$
1'
#1100
1$
#1200
0$
#1300
1$
#1400
0$
#1500
b11010110000 2
1$
b110101110100000 (
b110101110100000 /
#1600
0$
#1700
1$
#1800
0$
#1900
1$
#2000
0$
b10010001111111111111110101010 )
b10010001111111111111110101010 0
#2100
1$
#2200
0$
#2300
1$
#2400
0$
#2500
b1111 "
b1111 .
b1111 4
1$
1+
#2600
0$
#2700
1$
#2800
0$
#2900
1$
#3000
0$
0+
#3100
1$
#3200
0$
#3300
1$
#3400
0$
#3500
b110110110000 2
1$
b1101101100010000 (
b1101101100010000 /
#3600
0$
#3700
1$
#3800
0$
#3900
1$
#4000
0$
#4100
1$
#4200
0$
#4300
1$
#4400
0$
#4500
b111111 "
b111111 .
b111111 4
1$
1+
#4600
0$
#4700
1$
#4800
0$
#4900
1$
#5000
0$
0+
#5100
1$
#5200
0$
#5300
1$
#5400
0$
#5500
b111111111111 2
1$
b1111111111111111 (
b1111111111111111 /
#5600
0$
#5700
1$
#5800
0$
#5900
1$
#6000
0$
#6100
1$
#6200
0$
#6300
1$
#6400
0$
#6500
1$
1+
#6600
0$
#6700
1$
#6800
0$
#6900
1$
#7000
0$
0+
#7100
1$
#7200
0$
#7300
1$
#7400
0$
#7500
b0 "
b0 .
b0 4
1$
0'
#7600
0$
#7700
1$
#7800
0$
#7900
1$
#8000
0$
1'
#8100
1$
#8200
0$
#8300
1$
#8400
0$
#8500
1$
b10010001111111111111110101010 %
b10010001111111111111110101010 ,
#8600
0$
#8700
1$
#8800
0$
#8900
1$
#9000
b10010001111111111111110101010 #
b10010001111111111111110101010 -
b10010001111111111111110101010 3
0$
1&
#9100
1$
#9200
0$
#9300
1$
#9400
0$
#9500
1$
0&
#9600
0$
#9700
1$
#9800
0$
#9900
1$
#10000
b11010110000 2
0$
b110101110100000 (
b110101110100000 /
#10100
1$
#10200
0$
#10300
1$
#10400
0$
#10500
b101000000000 !
b101000000000 1
b101000000000 5
1$
1*
#10600
0$
#10700
1$
#10800
0$
#10900
1$
#11000
0$
0*
#11100
1$
#11200
0$
#11300
1$
#11400
0$
#11500
1$
#11600
0$
#11700
1$
#11800
0$
#11900
1$
#12000
0$
1&
#12100
1$
#12200
0$
#12300
1$
#12400
0$
#12500
1$
0&
#12600
0$
#12700
1$
#12800
0$
#12900
1$
#13000
b110110110000 2
0$
b1101101100010000 (
b1101101100010000 /
#13100
1$
#13200
0$
#13300
1$
#13400
0$
#13500
b101000000000000000000000 !
b101000000000000000000000 1
b101000000000000000000000 5
1$
1*
#13600
0$
#13700
1$
#13800
0$
#13900
1$
#14000
0$
0*
#14100
1$
#14200
0$
#14300
1$
#14400
0$
#14500
1$
#14600
0$
#14700
1$
#14800
0$
#14900
1$
#15000
0$
1&
#15100
1$
#15200
0$
#15300
1$
#15400
0$
#15500
1$
0&
#15600
0$
#15700
1$
#15800
0$
#15900
1$
#16000
b111111111111 2
0$
b1111111111111111 (
b1111111111111111 /
#16100
1$
#16200
0$
#16300
1$
#16400
0$
#16500
1$
1*
#16600
0$
#16700
1$
#16800
0$
#16900
1$
#17000
0$
0*
#17100
1$
#17200
0$
#17300
1$
#17400
0$
#17500
b0 #
b0 -
b0 3
b0 !
b0 1
b0 5
1$
0'
#17600
0$
#17700
1$
#17800
0$
#17900
1$
#18000
0$
1'
