GpioEmu.v
module GpioEmu(n_reset, saddress[15:0], srd, swr, sdata_in[31:0], sdata_out[31:0], gpio_in[31:0], gpio_latch, gpio_out[31:0], clk, gpio_in_s_insp[31:0], counter[7:0]);

input n_reset;
input [15:0] saddress;
input srd;
input swr;
input [31:0] sdata_in;
input [31:0] gpio_in;
input gpio_latch;
input clk;

output[31:0] sdata_out;
output [31:0] gpio_out;
output [31:0] gpio_in_s_insp;
output [7:0] counter;

reg [31:0] gpio_in_s;
reg [31:0] gpio_out_s;
reg [31:0] sdata_out_s;
reg [7:0] counter_s;
//reg count_flag;
reg int;


//Reset
always@(negedge n_reset) begin
    sdata_out_s <= 0;
    gpio_out_s <= 0;
    gpio_in_s <= 0;
    counter_s <= 8'h4e;
    int <= 0;
end

// odczyt na gpio
always@(posedge gpio_latch) begin
    gpio_in_s <= gpio_in;
end

always @(posedge clk) begin 
    //if(count_flag == 1) begin 
    if(counter_s >= 0)
        counter_s = counter_s - 1;
    else
        int <= 1;
    //end
end


wire [11:0] cut_address;
assign cut_address = {saddress[15:8], saddress[3:0]};

always@(posedge srd) begin
    if(cut_address == 12'h6b0)
        //sdata_out_s <= (gpio_in_s[3:0] << 8);
        sdata_out_s <= (gpio_in_s & 32'h0f) << 8;
    else if (cut_address == 12'hdb0) 
        sdata_out_s <= (gpio_in_s & 32'h0f) << 20;
        sdata_out_s <= (int << 4);
    // else 
    //     sdata_out_s <= 0;
end


always@(posedge swr) begin
    if(cut_address == 12'h6b0)
        gpio_out_s[3:0] <= sdata_in[11:8];  
    else if (cut_address == 12'hdb0) 
        gpio_out_s[7:4] <= sdata_in[23:20];  
        if (((sdata_in >> 4 ) & 1'b1) == 1)
            counter_s <= 8'h4e;
    // else 
    //     gpio_out_s <= gpio_out;
end

assign sdata_out = sdata_out_s;
assign gpio_out = gpio_out_s;
assign gpio_in_s_insp = gpio_in_s;
assign counter = counter_s;


endmodule

GpioEmu_tb.v
`timescale 1 ns /10 ps

module GpioEmu_tb;

	reg  n_reset = 1;
	reg[15:0] saddress = 0;
	reg[31:0] sdata_in = 0;
	reg[31:0] gpio_in = 0;
	reg gpio_latch = 0;
	reg clk= 0;
	reg srd = 0;
	reg swr = 0;

	wire[31:0] gpio_out_test;
	wire[31:0] sdata_out_test;
	wire[31:0] gpio_in_s_insp_test;
	wire[7:0] counter;

	initial begin
		$dumpfile("GpioEmu.vcd");
		$dumpvars(0,GpioEmu_tb);
	end
	
	always
		#1 clk= ~clk;

    initial begin 

        //reset
        # 5 n_reset = 0;
        # 5 n_reset = 1;

        //zapis 1 oś
        #5 saddress= 16'h6ba0;
		#5 sdata_in = 32'h123fffaa;
		#5 swr= 1;
		#5 swr= 0;

        //zapis 2 oś
        #5 saddress= 16'hdb10;
		#5 sdata_in = 32'h123fffaa;
		#5 swr= 1;
		#5 swr= 0;

        //zły zapis
        #5 saddress= 16'hffff;
		#5 sdata_in = 32'h123fffaa;
		#5 swr= 1;
		#5 swr= 0;

        //reset
        # 5 n_reset = 0;
        # 5 n_reset = 1;

        //odczyt z osi 1
		#5 gpio_in = 32'h123fffaa;
		#5 gpio_latch = 1;
		#5 gpio_latch = 0;
		#5 saddress= 16'h6ba0;
		#5 srd= 1;
		#5 srd= 0;
		
		//odczyt z osi 2
		#5 gpio_in = 32'h123fffaa;
		#5 gpio_latch = 1;
		#5 gpio_latch = 0;
		#5 saddress= 16'hdb10;;
		#5 srd= 1;
		#5 srd= 0;

		//odczyt ze złego adresu
		#5 gpio_in = 32'h123fffaa;
		#5 gpio_latch = 1;
		#5 gpio_latch = 0;
		#5 saddress= 16'hffff;
		#5 srd= 1;
		#5 srd= 0;

		//reset
		#5 n_reset = 0;
		#5 n_reset = 1;

		#300 srd= 1;
		#1500 $finish;

	end
	GpioEmu test1(n_reset, saddress, srd, swr, sdata_in, sdata_out_test, gpio_in, gpio_latch, gpio_out_test, clk, gpio_in_s_insp_test, counter);
endmodule

GpioEmu.vcd
$date
	Tue Apr 26 21:27:03 2022
$end
$version
	Icarus Verilog
$end
$timescale
	10ps
$end
$scope module GpioEmu_tb $end
$var wire 32 ! sdata_out_test [31:0] $end
$var wire 32 " gpio_out_test [31:0] $end
$var wire 32 # gpio_in_s_insp_test [31:0] $end
$var wire 8 $ counter [7:0] $end
$var reg 1 % clk $end
$var reg 32 & gpio_in [31:0] $end
$var reg 1 ' gpio_latch $end
$var reg 1 ( n_reset $end
$var reg 16 ) saddress [15:0] $end
$var reg 32 * sdata_in [31:0] $end
$var reg 1 + srd $end
$var reg 1 , swr $end
$scope module test1 $end
$var wire 1 % clk $end
$var wire 8 - counter [7:0] $end
$var wire 32 . gpio_in [31:0] $end
$var wire 32 / gpio_in_s_insp [31:0] $end
$var wire 1 ' gpio_latch $end
$var wire 32 0 gpio_out [31:0] $end
$var wire 1 ( n_reset $end
$var wire 16 1 saddress [15:0] $end
$var wire 32 2 sdata_in [31:0] $end
$var wire 32 3 sdata_out [31:0] $end
$var wire 1 + srd $end
$var wire 1 , swr $end
$var wire 12 4 cut_address [11:0] $end
$var reg 8 5 counter_s [7:0] $end
$var reg 32 6 gpio_in_s [31:0] $end
$var reg 32 7 gpio_out_s [31:0] $end
$var reg 1 8 int $end
$var reg 32 9 sdata_out_s [31:0] $end
$upscope $end
$upscope $end
$enddefinitions $end
#0
$dumpvars
bx 9
x8
bx 7
bx 6
bx 5
b0 4
bx 3
b0 2
b0 1
bx 0
bx /
b0 .
bx -
0,
0+
b0 *
b0 )
1(
0'
b0 &
0%
bx $
bx #
bx "
bx !
$end
#100
18
1%
#200
0%
#300
1%
#400
0%
#500
18
b1001110 $
b1001110 -
b1001110 5
b0 #
b0 /
b0 6
b0 "
b0 0
b0 7
b0 !
b0 3
b0 9
1%
0(
#600
0%
#700
b1001101 $
b1001101 -
b1001101 5
1%
#800
0%
#900
b1001100 $
b1001100 -
b1001100 5
1%
#1000
0%
1(
#1100
b1001011 $
b1001011 -
b1001011 5
1%
#1200
0%
#1300
b1001010 $
b1001010 -
b1001010 5
1%
#1400
0%
#1500
b1001001 $
b1001001 -
b1001001 5
b11010110000 4
1%
b110101110100000 )
b110101110100000 1
#1600
0%
#1700
b1001000 $
b1001000 -
b1001000 5
1%
#1800
0%
#1900
b1000111 $
b1000111 -
b1000111 5
1%
#2000
0%
b10010001111111111111110101010 *
b10010001111111111111110101010 2
#2100
b1000110 $
b1000110 -
b1000110 5
1%
#2200
0%
#2300
b1000101 $
b1000101 -
b1000101 5
1%
#2400
0%
#2500
b1111 "
b1111 0
b1111 7
b1000100 $
b1000100 -
b1000100 5
1%
1,
#2600
0%
#2700
b1000011 $
b1000011 -
b1000011 5
1%
#2800
0%
#2900
b1000010 $
b1000010 -
b1000010 5
1%
#3000
0%
0,
#3100
b1000001 $
b1000001 -
b1000001 5
1%
#3200
0%
#3300
b1000000 $
b1000000 -
b1000000 5
1%
#3400
0%
#3500
b111111 $
b111111 -
b111111 5
b110110110000 4
1%
b1101101100010000 )
b1101101100010000 1
#3600
0%
#3700
b111110 $
b111110 -
b111110 5
1%
#3800
0%
#3900
b111101 $
b111101 -
b111101 5
1%
#4000
0%
#4100
b111100 $
b111100 -
b111100 5
1%
#4200
0%
#4300
b111011 $
b111011 -
b111011 5
1%
#4400
0%
#4500
b111111 "
b111111 0
b111111 7
b111010 $
b111010 -
b111010 5
1%
1,
#4600
0%
#4700
b111001 $
b111001 -
b111001 5
1%
#4800
0%
#4900
b111000 $
b111000 -
b111000 5
1%
#5000
0%
0,
#5100
b110111 $
b110111 -
b110111 5
1%
#5200
0%
#5300
b110110 $
b110110 -
b110110 5
1%
#5400
0%
#5500
b110101 $
b110101 -
b110101 5
b111111111111 4
1%
b1111111111111111 )
b1111111111111111 1
#5600
0%
#5700
b110100 $
b110100 -
b110100 5
1%
#5800
0%
#5900
b110011 $
b110011 -
b110011 5
1%
#6000
0%
#6100
b110010 $
b110010 -
b110010 5
1%
#6200
0%
#6300
b110001 $
b110001 -
b110001 5
1%
#6400
0%
#6500
b110000 $
b110000 -
b110000 5
1%
1,
#6600
0%
#6700
b101111 $
b101111 -
b101111 5
1%
#6800
0%
#6900
b101110 $
b101110 -
b101110 5
1%
#7000
0%
0,
#7100
b101101 $
b101101 -
b101101 5
1%
#7200
0%
#7300
b101100 $
b101100 -
b101100 5
1%
#7400
0%
#7500
08
b0 "
b0 0
b0 7
b1001110 $
b1001110 -
b1001110 5
1%
0(
#7600
0%
#7700
b1001101 $
b1001101 -
b1001101 5
1%
#7800
0%
#7900
b1001100 $
b1001100 -
b1001100 5
1%
#8000
0%
1(
#8100
b1001011 $
b1001011 -
b1001011 5
1%
#8200
0%
#8300
b1001010 $
b1001010 -
b1001010 5
1%
#8400
0%
#8500
b1001001 $
b1001001 -
b1001001 5
1%
b10010001111111111111110101010 &
b10010001111111111111110101010 .
#8600
0%
#8700
b1001000 $
b1001000 -
b1001000 5
1%
#8800
0%
#8900
b1000111 $
b1000111 -
b1000111 5
1%
#9000
b10010001111111111111110101010 #
b10010001111111111111110101010 /
b10010001111111111111110101010 6
0%
1'
#9100
b1000110 $
b1000110 -
b1000110 5
1%
#9200
0%
#9300
b1000101 $
b1000101 -
b1000101 5
1%
#9400
0%
#9500
b1000100 $
b1000100 -
b1000100 5
1%
0'
#9600
0%
#9700
b1000011 $
b1000011 -
b1000011 5
1%
#9800
0%
#9900
b1000010 $
b1000010 -
b1000010 5
1%
#10000
b11010110000 4
0%
b110101110100000 )
b110101110100000 1
#10100
b1000001 $
b1000001 -
b1000001 5
1%
#10200
0%
#10300
b1000000 $
b1000000 -
b1000000 5
1%
#10400
0%
#10500
b0 !
b0 3
b0 9
b111111 $
b111111 -
b111111 5
1%
1+
#10600
0%
#10700
b111110 $
b111110 -
b111110 5
1%
#10800
0%
#10900
b111101 $
b111101 -
b111101 5
1%
#11000
0%
0+
#11100
b111100 $
b111100 -
b111100 5
1%
#11200
0%
#11300
b111011 $
b111011 -
b111011 5
1%
#11400
0%
#11500
b111010 $
b111010 -
b111010 5
1%
#11600
0%
#11700
b111001 $
b111001 -
b111001 5
1%
#11800
0%
#11900
b111000 $
b111000 -
b111000 5
1%
#12000
0%
1'
#12100
b110111 $
b110111 -
b110111 5
1%
#12200
0%
#12300
b110110 $
b110110 -
b110110 5
1%
#12400
0%
#12500
b110101 $
b110101 -
b110101 5
1%
0'
#12600
0%
#12700
b110100 $
b110100 -
b110100 5
1%
#12800
0%
#12900
b110011 $
b110011 -
b110011 5
1%
#13000
b110110110000 4
0%
b1101101100010000 )
b1101101100010000 1
#13100
b110010 $
b110010 -
b110010 5
1%
#13200
0%
#13300
b110001 $
b110001 -
b110001 5
1%
#13400
0%
#13500
b0 !
b0 3
b0 9
b110000 $
b110000 -
b110000 5
1%
1+
#13600
0%
#13700
b101111 $
b101111 -
b101111 5
1%
#13800
0%
#13900
b101110 $
b101110 -
b101110 5
1%
#14000
0%
0+
#14100
b101101 $
b101101 -
b101101 5
1%
#14200
0%
#14300
b101100 $
b101100 -
b101100 5
1%
#14400
0%
#14500
b101011 $
b101011 -
b101011 5
1%
#14600
0%
#14700
b101010 $
b101010 -
b101010 5
1%
#14800
0%
#14900
b101001 $
b101001 -
b101001 5
1%
#15000
0%
1'
#15100
b101000 $
b101000 -
b101000 5
1%
#15200
0%
#15300
b100111 $
b100111 -
b100111 5
1%
#15400
0%
#15500
b100110 $
b100110 -
b100110 5
1%
0'
#15600
0%
#15700
b100101 $
b100101 -
b100101 5
1%
#15800
0%
#15900
b100100 $
b100100 -
b100100 5
1%
#16000
b111111111111 4
0%
b1111111111111111 )
b1111111111111111 1
#16100
b100011 $
b100011 -
b100011 5
1%
#16200
0%
#16300
b100010 $
b100010 -
b100010 5
1%
#16400
0%
#16500
b100001 $
b100001 -
b100001 5
1%
1+
#16600
0%
#16700
b100000 $
b100000 -
b100000 5
1%
#16800
0%
#16900
b11111 $
b11111 -
b11111 5
1%
#17000
0%
0+
#17100
b11110 $
b11110 -
b11110 5
1%
#17200
0%
#17300
b11101 $
b11101 -
b11101 5
1%
#17400
0%
#17500
b0 #
b0 /
b0 6
b1001110 $
b1001110 -
b1001110 5
1%
0(
#17600
0%
#17700
b1001101 $
b1001101 -
b1001101 5
1%
#17800
0%
#17900
b1001100 $
b1001100 -
b1001100 5
1%
#18000
0%
1(
#18100
b1001011 $
b1001011 -
b1001011 5
1%
#18200
0%
#18300
b1001010 $
b1001010 -
b1001010 5
1%
#18400
0%
#18500
b1001001 $
b1001001 -
b1001001 5
1%
#18600
0%
#18700
b1001000 $
b1001000 -
b1001000 5
1%
#18800
0%
#18900
b1000111 $
b1000111 -
b1000111 5
1%
#19000
0%
#19100
b1000110 $
b1000110 -
b1000110 5
1%
#19200
0%
#19300
b1000101 $
b1000101 -
b1000101 5
1%
#19400
0%
#19500
b1000100 $
b1000100 -
b1000100 5
1%
#19600
0%
#19700
b1000011 $
b1000011 -
b1000011 5
1%
#19800
0%
#19900
b1000010 $
b1000010 -
b1000010 5
1%
#20000
0%
#20100
b1000001 $
b1000001 -
b1000001 5
1%
#20200
0%
#20300
b1000000 $
b1000000 -
b1000000 5
1%
#20400
0%
#20500
b111111 $
b111111 -
b111111 5
1%
#20600
0%
#20700
b111110 $
b111110 -
b111110 5
1%
#20800
0%
#20900
b111101 $
b111101 -
b111101 5
1%
#21000
0%
#21100
b111100 $
b111100 -
b111100 5
1%
#21200
0%
#21300
b111011 $
b111011 -
b111011 5
1%
#21400
0%
#21500
b111010 $
b111010 -
b111010 5
1%
#21600
0%
#21700
b111001 $
b111001 -
b111001 5
1%
#21800
0%
#21900
b111000 $
b111000 -
b111000 5
1%
#22000
0%
#22100
b110111 $
b110111 -
b110111 5
1%
#22200
0%
#22300
b110110 $
b110110 -
b110110 5
1%
#22400
0%
#22500
b110101 $
b110101 -
b110101 5
1%
#22600
0%
#22700
b110100 $
b110100 -
b110100 5
1%
#22800
0%
#22900
b110011 $
b110011 -
b110011 5
1%
#23000
0%
#23100
b110010 $
b110010 -
b110010 5
1%
#23200
0%
#23300
b110001 $
b110001 -
b110001 5
1%
#23400
0%
#23500
b110000 $
b110000 -
b110000 5
1%
#23600
0%
#23700
b101111 $
b101111 -
b101111 5
1%
#23800
0%
#23900
b101110 $
b101110 -
b101110 5
1%
#24000
0%
#24100
b101101 $
b101101 -
b101101 5
1%
#24200
0%
#24300
b101100 $
b101100 -
b101100 5
1%
#24400
0%
#24500
b101011 $
b101011 -
b101011 5
1%
#24600
0%
#24700
b101010 $
b101010 -
b101010 5
1%
#24800
0%
#24900
b101001 $
b101001 -
b101001 5
1%
#25000
0%
#25100
b101000 $
b101000 -
b101000 5
1%
#25200
0%
#25300
b100111 $
b100111 -
b100111 5
1%
#25400
0%
#25500
b100110 $
b100110 -
b100110 5
1%
#25600
0%
#25700
b100101 $
b100101 -
b100101 5
1%
#25800
0%
#25900
b100100 $
b100100 -
b100100 5
1%
#26000
0%
#26100
b100011 $
b100011 -
b100011 5
1%
#26200
0%
#26300
b100010 $
b100010 -
b100010 5
1%
#26400
0%
#26500
b100001 $
b100001 -
b100001 5
1%
#26600
0%
#26700
b100000 $
b100000 -
b100000 5
1%
#26800
0%
#26900
b11111 $
b11111 -
b11111 5
1%
#27000
0%
#27100
b11110 $
b11110 -
b11110 5
1%
#27200
0%
#27300
b11101 $
b11101 -
b11101 5
1%
#27400
0%
#27500
b11100 $
b11100 -
b11100 5
1%
#27600
0%
#27700
b11011 $
b11011 -
b11011 5
1%
#27800
0%
#27900
b11010 $
b11010 -
b11010 5
1%
#28000
0%
#28100
b11001 $
b11001 -
b11001 5
1%
#28200
0%
#28300
b11000 $
b11000 -
b11000 5
1%
#28400
0%
#28500
b10111 $
b10111 -
b10111 5
1%
#28600
0%
#28700
b10110 $
b10110 -
b10110 5
1%
#28800
0%
#28900
b10101 $
b10101 -
b10101 5
1%
#29000
0%
#29100
b10100 $
b10100 -
b10100 5
1%
#29200
0%
#29300
b10011 $
b10011 -
b10011 5
1%
#29400
0%
#29500
b10010 $
b10010 -
b10010 5
1%
#29600
0%
#29700
b10001 $
b10001 -
b10001 5
1%
#29800
0%
#29900
b10000 $
b10000 -
b10000 5
1%
#30000
0%
#30100
b1111 $
b1111 -
b1111 5
1%
#30200
0%
#30300
b1110 $
b1110 -
b1110 5
1%
#30400
0%
#30500
b1101 $
b1101 -
b1101 5
1%
#30600
0%
#30700
b1100 $
b1100 -
b1100 5
1%
#30800
0%
#30900
b1011 $
b1011 -
b1011 5
1%
#31000
0%
#31100
b1010 $
b1010 -
b1010 5
1%
#31200
0%
#31300
b1001 $
b1001 -
b1001 5
1%
#31400
0%
#31500
b1000 $
b1000 -
b1000 5
1%
#31600
0%
#31700
b111 $
b111 -
b111 5
1%
#31800
0%
#31900
b110 $
b110 -
b110 5
1%
#32000
0%
#32100
b101 $
b101 -
b101 5
1%
#32200
0%
#32300
b100 $
b100 -
b100 5
1%
#32400
0%
#32500
b11 $
b11 -
b11 5
1%
#32600
0%
#32700
b10 $
b10 -
b10 5
1%
#32800
0%
#32900
b1 $
b1 -
b1 5
1%
#33000
0%
#33100
b0 $
b0 -
b0 5
1%
#33200
0%
#33300
b11111111 $
b11111111 -
b11111111 5
1%
#33400
0%
#33500
b11111110 $
b11111110 -
b11111110 5
1%
#33600
0%
#33700
b11111101 $
b11111101 -
b11111101 5
1%
#33800
0%
#33900
b11111100 $
b11111100 -
b11111100 5
1%
#34000
0%
#34100
b11111011 $
b11111011 -
b11111011 5
1%
#34200
0%
#34300
b11111010 $
b11111010 -
b11111010 5
1%
#34400
0%
#34500
b11111001 $
b11111001 -
b11111001 5
1%
#34600
0%
#34700
b11111000 $
b11111000 -
b11111000 5
1%
#34800
0%
#34900
b11110111 $
b11110111 -
b11110111 5
1%
#35000
0%
#35100
b11110110 $
b11110110 -
b11110110 5
1%
#35200
0%
#35300
b11110101 $
b11110101 -
b11110101 5
1%
#35400
0%
#35500
b11110100 $
b11110100 -
b11110100 5
1%
#35600
0%
#35700
b11110011 $
b11110011 -
b11110011 5
1%
#35800
0%
#35900
b11110010 $
b11110010 -
b11110010 5
1%
#36000
0%
#36100
b11110001 $
b11110001 -
b11110001 5
1%
#36200
0%
#36300
b11110000 $
b11110000 -
b11110000 5
1%
#36400
0%
#36500
b11101111 $
b11101111 -
b11101111 5
1%
#36600
0%
#36700
b11101110 $
b11101110 -
b11101110 5
1%
#36800
0%
#36900
b11101101 $
b11101101 -
b11101101 5
1%
#37000
0%
#37100
b11101100 $
b11101100 -
b11101100 5
1%
#37200
0%
#37300
b11101011 $
b11101011 -
b11101011 5
1%
#37400
0%
#37500
b11101010 $
b11101010 -
b11101010 5
1%
#37600
0%
#37700
b11101001 $
b11101001 -
b11101001 5
1%
#37800
0%
#37900
b11101000 $
b11101000 -
b11101000 5
1%
#38000
0%
#38100
b11100111 $
b11100111 -
b11100111 5
1%
#38200
0%
#38300
b11100110 $
b11100110 -
b11100110 5
1%
#38400
0%
#38500
b11100101 $
b11100101 -
b11100101 5
1%
#38600
0%
#38700
b11100100 $
b11100100 -
b11100100 5
1%
#38800
0%
#38900
b11100011 $
b11100011 -
b11100011 5
1%
#39000
0%
#39100
b11100010 $
b11100010 -
b11100010 5
1%
#39200
0%
#39300
b11100001 $
b11100001 -
b11100001 5
1%
#39400
0%
#39500
b11100000 $
b11100000 -
b11100000 5
1%
#39600
0%
#39700
b11011111 $
b11011111 -
b11011111 5
1%
#39800
0%
#39900
b11011110 $
b11011110 -
b11011110 5
1%
#40000
0%
#40100
b11011101 $
b11011101 -
b11011101 5
1%
#40200
0%
#40300
b11011100 $
b11011100 -
b11011100 5
1%
#40400
0%
#40500
b11011011 $
b11011011 -
b11011011 5
1%
#40600
0%
#40700
b11011010 $
b11011010 -
b11011010 5
1%
#40800
0%
#40900
b11011001 $
b11011001 -
b11011001 5
1%
#41000
0%
#41100
b11011000 $
b11011000 -
b11011000 5
1%
#41200
0%
#41300
b11010111 $
b11010111 -
b11010111 5
1%
#41400
0%
#41500
b11010110 $
b11010110 -
b11010110 5
1%
#41600
0%
#41700
b11010101 $
b11010101 -
b11010101 5
1%
#41800
0%
#41900
b11010100 $
b11010100 -
b11010100 5
1%
#42000
0%
#42100
b11010011 $
b11010011 -
b11010011 5
1%
#42200
0%
#42300
b11010010 $
b11010010 -
b11010010 5
1%
#42400
0%
#42500
b11010001 $
b11010001 -
b11010001 5
1%
#42600
0%
#42700
b11010000 $
b11010000 -
b11010000 5
1%
#42800
0%
#42900
b11001111 $
b11001111 -
b11001111 5
1%
#43000
0%
#43100
b11001110 $
b11001110 -
b11001110 5
1%
#43200
0%
#43300
b11001101 $
b11001101 -
b11001101 5
1%
#43400
0%
#43500
b11001100 $
b11001100 -
b11001100 5
1%
#43600
0%
#43700
b11001011 $
b11001011 -
b11001011 5
1%
#43800
0%
#43900
b11001010 $
b11001010 -
b11001010 5
1%
#44000
0%
#44100
b11001001 $
b11001001 -
b11001001 5
1%
#44200
0%
#44300
b11001000 $
b11001000 -
b11001000 5
1%
#44400
0%
#44500
b11000111 $
b11000111 -
b11000111 5
1%
#44600
0%
#44700
b11000110 $
b11000110 -
b11000110 5
1%
#44800
0%
#44900
b11000101 $
b11000101 -
b11000101 5
1%
#45000
0%
#45100
b11000100 $
b11000100 -
b11000100 5
1%
#45200
0%
#45300
b11000011 $
b11000011 -
b11000011 5
1%
#45400
0%
#45500
b11000010 $
b11000010 -
b11000010 5
1%
#45600
0%
#45700
b11000001 $
b11000001 -
b11000001 5
1%
#45800
0%
#45900
b11000000 $
b11000000 -
b11000000 5
1%
#46000
0%
#46100
b10111111 $
b10111111 -
b10111111 5
1%
#46200
0%
#46300
b10111110 $
b10111110 -
b10111110 5
1%
#46400
0%
#46500
b10111101 $
b10111101 -
b10111101 5
1%
#46600
0%
#46700
b10111100 $
b10111100 -
b10111100 5
1%
#46800
0%
#46900
b10111011 $
b10111011 -
b10111011 5
1%
#47000
0%
#47100
b10111010 $
b10111010 -
b10111010 5
1%
#47200
0%
#47300
b10111001 $
b10111001 -
b10111001 5
1%
#47400
0%
#47500
b10111000 $
b10111000 -
b10111000 5
1%
#47600
0%
#47700
b10110111 $
b10110111 -
b10110111 5
1%
#47800
0%
#47900
b10110110 $
b10110110 -
b10110110 5
1%
#48000
0%
1+
#48100
b10110101 $
b10110101 -
b10110101 5
1%
#48200
0%
#48300
b10110100 $
b10110100 -
b10110100 5
1%
#48400
0%
#48500
b10110011 $
b10110011 -
b10110011 5
1%
#48600
0%
#48700
b10110010 $
b10110010 -
b10110010 5
1%
#48800
0%
#48900
b10110001 $
b10110001 -
b10110001 5
1%
#49000
0%
#49100
b10110000 $
b10110000 -
b10110000 5
1%
#49200
0%
#49300
b10101111 $
b10101111 -
b10101111 5
1%
#49400
0%
#49500
b10101110 $
b10101110 -
b10101110 5
1%
#49600
0%
#49700
b10101101 $
b10101101 -
b10101101 5
1%
#49800
0%
#49900
b10101100 $
b10101100 -
b10101100 5
1%
#50000
0%
#50100
b10101011 $
b10101011 -
b10101011 5
1%
#50200
0%
#50300
b10101010 $
b10101010 -
b10101010 5
1%
#50400
0%
#50500
b10101001 $
b10101001 -
b10101001 5
1%
#50600
0%
#50700
b10101000 $
b10101000 -
b10101000 5
1%
#50800
0%
#50900
b10100111 $
b10100111 -
b10100111 5
1%
#51000
0%
#51100
b10100110 $
b10100110 -
b10100110 5
1%
#51200
0%
#51300
b10100101 $
b10100101 -
b10100101 5
1%
#51400
0%
#51500
b10100100 $
b10100100 -
b10100100 5
1%
#51600
0%
#51700
b10100011 $
b10100011 -
b10100011 5
1%
#51800
0%
#51900
b10100010 $
b10100010 -
b10100010 5
1%
#52000
0%
#52100
b10100001 $
b10100001 -
b10100001 5
1%
#52200
0%
#52300
b10100000 $
b10100000 -
b10100000 5
1%
#52400
0%
#52500
b10011111 $
b10011111 -
b10011111 5
1%
#52600
0%
#52700
b10011110 $
b10011110 -
b10011110 5
1%
#52800
0%
#52900
b10011101 $
b10011101 -
b10011101 5
1%
#53000
0%
#53100
b10011100 $
b10011100 -
b10011100 5
1%
#53200
0%
#53300
b10011011 $
b10011011 -
b10011011 5
1%
#53400
0%
#53500
b10011010 $
b10011010 -
b10011010 5
1%
#53600
0%
#53700
b10011001 $
b10011001 -
b10011001 5
1%
#53800
0%
#53900
b10011000 $
b10011000 -
b10011000 5
1%
#54000
0%
#54100
b10010111 $
b10010111 -
b10010111 5
1%
#54200
0%
#54300
b10010110 $
b10010110 -
b10010110 5
1%
#54400
0%
#54500
b10010101 $
b10010101 -
b10010101 5
1%
#54600
0%
#54700
b10010100 $
b10010100 -
b10010100 5
1%
#54800
0%
#54900
b10010011 $
b10010011 -
b10010011 5
1%
#55000
0%
#55100
b10010010 $
b10010010 -
b10010010 5
1%
#55200
0%
#55300
b10010001 $
b10010001 -
b10010001 5
1%
#55400
0%
#55500
b10010000 $
b10010000 -
b10010000 5
1%
#55600
0%
#55700
b10001111 $
b10001111 -
b10001111 5
1%
#55800
0%
#55900
b10001110 $
b10001110 -
b10001110 5
1%
#56000
0%
#56100
b10001101 $
b10001101 -
b10001101 5
1%
#56200
0%
#56300
b10001100 $
b10001100 -
b10001100 5
1%
#56400
0%
#56500
b10001011 $
b10001011 -
b10001011 5
1%
#56600
0%
#56700
b10001010 $
b10001010 -
b10001010 5
1%
#56800
0%
#56900
b10001001 $
b10001001 -
b10001001 5
1%
#57000
0%
#57100
b10001000 $
b10001000 -
b10001000 5
1%
#57200
0%
#57300
b10000111 $
b10000111 -
b10000111 5
1%
#57400
0%
#57500
b10000110 $
b10000110 -
b10000110 5
1%
#57600
0%
#57700
b10000101 $
b10000101 -
b10000101 5
1%
#57800
0%
#57900
b10000100 $
b10000100 -
b10000100 5
1%
#58000
0%
#58100
b10000011 $
b10000011 -
b10000011 5
1%
#58200
0%
#58300
b10000010 $
b10000010 -
b10000010 5
1%
#58400
0%
#58500
b10000001 $
b10000001 -
b10000001 5
1%
#58600
0%
#58700
b10000000 $
b10000000 -
b10000000 5
1%
#58800
0%
#58900
b1111111 $
b1111111 -
b1111111 5
1%
#59000
0%
#59100
b1111110 $
b1111110 -
b1111110 5
1%
#59200
0%
#59300
b1111101 $
b1111101 -
b1111101 5
1%
#59400
0%
#59500
b1111100 $
b1111100 -
b1111100 5
1%
#59600
0%
#59700
b1111011 $
b1111011 -
b1111011 5
1%
#59800
0%
#59900
b1111010 $
b1111010 -
b1111010 5
1%
#60000
0%
#60100
b1111001 $
b1111001 -
b1111001 5
1%
#60200
0%
#60300
b1111000 $
b1111000 -
b1111000 5
1%
#60400
0%
#60500
b1110111 $
b1110111 -
b1110111 5
1%
#60600
0%
#60700
b1110110 $
b1110110 -
b1110110 5
1%
#60800
0%
#60900
b1110101 $
b1110101 -
b1110101 5
1%
#61000
0%
#61100
b1110100 $
b1110100 -
b1110100 5
1%
#61200
0%
#61300
b1110011 $
b1110011 -
b1110011 5
1%
#61400
0%
#61500
b1110010 $
b1110010 -
b1110010 5
1%
#61600
0%
#61700
b1110001 $
b1110001 -
b1110001 5
1%
#61800
0%
#61900
b1110000 $
b1110000 -
b1110000 5
1%
#62000
0%
#62100
b1101111 $
b1101111 -
b1101111 5
1%
#62200
0%
#62300
b1101110 $
b1101110 -
b1101110 5
1%
#62400
0%
#62500
b1101101 $
b1101101 -
b1101101 5
1%
#62600
0%
#62700
b1101100 $
b1101100 -
b1101100 5
1%
#62800
0%
#62900
b1101011 $
b1101011 -
b1101011 5
1%
#63000
0%
#63100
b1101010 $
b1101010 -
b1101010 5
1%
#63200
0%
#63300
b1101001 $
b1101001 -
b1101001 5
1%
#63400
0%
#63500
b1101000 $
b1101000 -
b1101000 5
1%
#63600
0%
#63700
b1100111 $
b1100111 -
b1100111 5
1%
#63800
0%
#63900
b1100110 $
b1100110 -
b1100110 5
1%
#64000
0%
#64100
b1100101 $
b1100101 -
b1100101 5
1%
#64200
0%
#64300
b1100100 $
b1100100 -
b1100100 5
1%
#64400
0%
#64500
b1100011 $
b1100011 -
b1100011 5
1%
#64600
0%
#64700
b1100010 $
b1100010 -
b1100010 5
1%
#64800
0%
#64900
b1100001 $
b1100001 -
b1100001 5
1%
#65000
0%
#65100
b1100000 $
b1100000 -
b1100000 5
1%
#65200
0%
#65300
b1011111 $
b1011111 -
b1011111 5
1%
#65400
0%
#65500
b1011110 $
b1011110 -
b1011110 5
1%
#65600
0%
#65700
b1011101 $
b1011101 -
b1011101 5
1%
#65800
0%
#65900
b1011100 $
b1011100 -
b1011100 5
1%
#66000
0%
#66100
b1011011 $
b1011011 -
b1011011 5
1%
#66200
0%
#66300
b1011010 $
b1011010 -
b1011010 5
1%
#66400
0%
#66500
b1011001 $
b1011001 -
b1011001 5
1%
#66600
0%
#66700
b1011000 $
b1011000 -
b1011000 5
1%
#66800
0%
#66900
b1010111 $
b1010111 -
b1010111 5
1%
#67000
0%
#67100
b1010110 $
b1010110 -
b1010110 5
1%
#67200
0%
#67300
b1010101 $
b1010101 -
b1010101 5
1%
#67400
0%
#67500
b1010100 $
b1010100 -
b1010100 5
1%
#67600
0%
#67700
b1010011 $
b1010011 -
b1010011 5
1%
#67800
0%
#67900
b1010010 $
b1010010 -
b1010010 5
1%
#68000
0%
#68100
b1010001 $
b1010001 -
b1010001 5
1%
#68200
0%
#68300
b1010000 $
b1010000 -
b1010000 5
1%
#68400
0%
#68500
b1001111 $
b1001111 -
b1001111 5
1%
#68600
0%
#68700
b1001110 $
b1001110 -
b1001110 5
1%
#68800
0%
#68900
b1001101 $
b1001101 -
b1001101 5
1%
#69000
0%
#69100
b1001100 $
b1001100 -
b1001100 5
1%
#69200
0%
#69300
b1001011 $
b1001011 -
b1001011 5
1%
