GpioEmu.v
module GpioEmu(n_reset, saddress[15:0], srd, swr, sdata_in[31:0], sdata_out[31:0], gpio_in[31:0], gpio_latch, gpio_out[31:0], clk, gpio_in_s_insp[31:0], counter[7:0]);

input n_reset;
input [15:0] saddress;
input srd;
input swr;
input [31:0] sdata_in;
input [31:0] gpio_in;
input gpio_latch;
input clk;

output[31:0] sdata_out;
output [31:0] gpio_out;
output [31:0] gpio_in_s_insp;
output [7:0] counter;

reg [31:0] gpio_in_s;
reg [31:0] gpio_out_s;
reg [31:0] sdata_out_s;
reg [7:0] counter_s;
//reg count_flag;
reg int;


//Reset
always@(negedge n_reset) begin
    sdata_out_s <= 0;
    gpio_out_s <= 0;
    gpio_in_s <= 0;
    counter_s <= 8'h4e;
    int <= 0;
end

// odczyt na gpio
always@(posedge gpio_latch) begin
    gpio_in_s <= gpio_in;
end

always @(posedge clk) begin 
    //if(count_flag == 1) begin 
    if(counter_s >= 0)
        counter_s = counter_s - 1;
    else
        int <= 1;
    //end
end


wire [11:0] cut_address;
assign cut_address = {saddress[15:8], saddress[3:0]};

always@(posedge srd) begin
    if(cut_address == 12'h6b0)
        //sdata_out_s <= (gpio_in_s[3:0] << 8);
        sdata_out_s <= (gpio_in_s & 32'h0f) << 8;
    else if (cut_address == 12'hdb0) 
        sdata_out_s <= (gpio_in_s & 32'h0f) << 20;
        sdata_out_s <= (int << 4);
    // else 
    //     sdata_out_s <= 0;
end


always@(posedge swr) begin
    if(cut_address == 12'h6b0)
        gpio_out_s[3:0] <= sdata_in[11:8];  
    else if (cut_address == 12'hdb0) 
        gpio_out_s[7:4] <= sdata_in[23:20];  
        if (((sdata_in >> 4 ) & 1'b1) == 1)
            counter_s <= 8'h4e;
    // else 
    //     gpio_out_s <= gpio_out;
end

assign sdata_out = sdata_out_s;
assign gpio_out = gpio_out_s;
assign gpio_in_s_insp = gpio_in_s;
assign counter = counter_s;


endmodule

GpioEmu_tb.v
`timescale 1 ns /10 ps

module GpioEmu_tb;

	reg  n_reset = 1;
	reg[15:0] saddress = 0;
	reg[31:0] sdata_in = 0;
	reg[31:0] gpio_in = 0;
	reg gpio_latch = 0;
	reg clk= 0;
	reg srd = 0;
	reg swr = 0;

	wire[31:0] gpio_out_test;
	wire[31:0] sdata_out_test;
	wire[31:0] gpio_in_s_insp_test;
	wire[7:0] counter = 0;

	initial begin
		$dumpfile("GpioEmu.vcd");
		$dumpvars(0,GpioEmu_tb);
	end
	
	always
		#1 clk= ~clk;

    initial begin 

        //reset
        # 5 n_reset = 0;
        # 5 n_reset = 1;

        //zapis 1 oś
        #5 saddress= 16'h6ba0;
		#5 sdata_in = 32'h123fffaa;
		#5 swr= 1;
		#5 swr= 0;

        //zapis 2 oś
        #5 saddress= 16'hdb10;
		#5 sdata_in = 32'h123fffaa;
		#5 swr= 1;
		#5 swr= 0;

        //zły zapis
        #5 saddress= 16'hffff;
		#5 sdata_in = 32'h123fffaa;
		#5 swr= 1;
		#5 swr= 0;

        //reset
        # 5 n_reset = 0;
        # 5 n_reset = 1;

        //odczyt z osi 1
		#5 gpio_in = 32'h123fffaa;
		#5 gpio_latch = 1;
		#5 gpio_latch = 0;
		#5 saddress= 16'h6ba0;
		#5 srd= 1;
		#5 srd= 0;
		
		//odczyt z osi 2
		#5 gpio_in = 32'h123fffaa;
		#5 gpio_latch = 1;
		#5 gpio_latch = 0;
		#5 saddress= 16'hdb10;;
		#5 srd= 1;
		#5 srd= 0;

		//odczyt ze złego adresu
		#5 gpio_in = 32'h123fffaa;
		#5 gpio_latch = 1;
		#5 gpio_latch = 0;
		#5 saddress= 16'hffff;
		#5 srd= 1;
		#5 srd= 0;

		//reset
		#5 n_reset = 0;
		#5 n_reset = 1;

		#300 srd= 1;
		#1500 $finish;

	end
	GpioEmu test1(n_reset, saddress, srd, swr, sdata_in, sdata_out_test, gpio_in, gpio_latch, gpio_out_test, clk, gpio_in_s_insp_test, counter);
endmodule

GpioEmu.vcd
$date
	Tue Apr 26 21:16:21 2022
$end
$version
	Icarus Verilog
$end
$timescale
	10ps
$end
$scope module GpioEmu_tb $end
$var wire 8 ! counter [7:0] $end
$var wire 32 " sdata_out_test [31:0] $end
$var wire 32 # gpio_out_test [31:0] $end
$var wire 32 $ gpio_in_s_insp_test [31:0] $end
$var reg 1 % clk $end
$var reg 32 & gpio_in [31:0] $end
$var reg 1 ' gpio_latch $end
$var reg 1 ( n_reset $end
$var reg 16 ) saddress [15:0] $end
$var reg 32 * sdata_in [31:0] $end
$var reg 1 + srd $end
$var reg 1 , swr $end
$scope module test1 $end
$var wire 1 % clk $end
$var wire 8 - counter [7:0] $end
$var wire 32 . gpio_in [31:0] $end
$var wire 32 / gpio_in_s_insp [31:0] $end
$var wire 1 ' gpio_latch $end
$var wire 32 0 gpio_out [31:0] $end
$var wire 1 ( n_reset $end
$var wire 16 1 saddress [15:0] $end
$var wire 32 2 sdata_in [31:0] $end
$var wire 32 3 sdata_out [31:0] $end
$var wire 1 + srd $end
$var wire 1 , swr $end
$var wire 12 4 cut_address [11:0] $end
$var reg 8 5 counter_s [7:0] $end
$var reg 32 6 gpio_in_s [31:0] $end
$var reg 32 7 gpio_out_s [31:0] $end
$var reg 1 8 int $end
$var reg 32 9 sdata_out_s [31:0] $end
$upscope $end
$upscope $end
$enddefinitions $end
#0
$dumpvars
bx 9
x8
bx 7
bx 6
bx 5
b0 4
bx 3
b0 2
b0 1
bx 0
bx /
b0 .
bx -
0,
0+
b0 *
b0 )
1(
0'
b0 &
0%
bx $
bx #
bx "
bx !
$end
#100
18
1%
#200
0%
#300
1%
#400
0%
#500
18
b0x00xxx0 !
b0x00xxx0 -
b1001110 5
b0 $
b0 /
b0 6
b0 #
b0 0
b0 7
b0 "
b0 3
b0 9
1%
0(
#600
0%
#700
b0x00xx0x !
b0x00xx0x -
b1001101 5
1%
#800
0%
#900
b0x00xx00 !
b0x00xx00 -
b1001100 5
1%
#1000
0%
1(
#1100
b0x00x0xx !
b0x00x0xx -
b1001011 5
1%
#1200
0%
#1300
b0x00x0x0 !
b0x00x0x0 -
b1001010 5
1%
#1400
0%
#1500
b0x00x00x !
b0x00x00x -
b1001001 5
b11010110000 4
1%
b110101110100000 )
b110101110100000 1
#1600
0%
#1700
b0x00x000 !
b0x00x000 -
b1001000 5
1%
#1800
0%
#1900
b0x000xxx !
b0x000xxx -
b1000111 5
1%
#2000
0%
b10010001111111111111110101010 *
b10010001111111111111110101010 2
#2100
b0x000xx0 !
b0x000xx0 -
b1000110 5
1%
#2200
0%
#2300
b0x000x0x !
b0x000x0x -
b1000101 5
1%
#2400
0%
#2500
b1111 #
b1111 0
b1111 7
b0x000x00 !
b0x000x00 -
b1000100 5
1%
1,
#2600
0%
#2700
b0x0000xx !
b0x0000xx -
b1000011 5
1%
#2800
0%
#2900
b0x0000x0 !
b0x0000x0 -
b1000010 5
1%
#3000
0%
0,
#3100
b0x00000x !
b0x00000x -
b1000001 5
1%
#3200
0%
#3300
b0x000000 !
b0x000000 -
b1000000 5
1%
#3400
0%
#3500
b0xxxxxx !
b0xxxxxx -
b111111 5
b110110110000 4
1%
b1101101100010000 )
b1101101100010000 1
#3600
0%
#3700
b0xxxxx0 !
b0xxxxx0 -
b111110 5
1%
#3800
0%
#3900
b0xxxx0x !
b0xxxx0x -
b111101 5
1%
#4000
0%
#4100
b0xxxx00 !
b0xxxx00 -
b111100 5
1%
#4200
0%
#4300
b0xxx0xx !
b0xxx0xx -
b111011 5
1%
#4400
0%
#4500
b111111 #
b111111 0
b111111 7
b0xxx0x0 !
b0xxx0x0 -
b111010 5
1%
1,
#4600
0%
#4700
b0xxx00x !
b0xxx00x -
b111001 5
1%
#4800
0%
#4900
b0xxx000 !
b0xxx000 -
b111000 5
1%
#5000
0%
0,
#5100
b0xx0xxx !
b0xx0xxx -
b110111 5
1%
#5200
0%
#5300
b0xx0xx0 !
b0xx0xx0 -
b110110 5
1%
#5400
0%
#5500
b0xx0x0x !
b0xx0x0x -
b110101 5
b111111111111 4
1%
b1111111111111111 )
b1111111111111111 1
#5600
0%
#5700
b0xx0x00 !
b0xx0x00 -
b110100 5
1%
#5800
0%
#5900
b0xx00xx !
b0xx00xx -
b110011 5
1%
#6000
0%
#6100
b0xx00x0 !
b0xx00x0 -
b110010 5
1%
#6200
0%
#6300
b0xx000x !
b0xx000x -
b110001 5
1%
#6400
0%
#6500
b0xx0000 !
b0xx0000 -
b110000 5
1%
1,
#6600
0%
#6700
b0x0xxxx !
b0x0xxxx -
b101111 5
1%
#6800
0%
#6900
b0x0xxx0 !
b0x0xxx0 -
b101110 5
1%
#7000
0%
0,
#7100
b0x0xx0x !
b0x0xx0x -
b101101 5
1%
#7200
0%
#7300
b0x0xx00 !
b0x0xx00 -
b101100 5
1%
#7400
0%
#7500
08
b0 #
b0 0
b0 7
b0x00xxx0 !
b0x00xxx0 -
b1001110 5
1%
0(
#7600
0%
#7700
b0x00xx0x !
b0x00xx0x -
b1001101 5
1%
#7800
0%
#7900
b0x00xx00 !
b0x00xx00 -
b1001100 5
1%
#8000
0%
1(
#8100
b0x00x0xx !
b0x00x0xx -
b1001011 5
1%
#8200
0%
#8300
b0x00x0x0 !
b0x00x0x0 -
b1001010 5
1%
#8400
0%
#8500
b0x00x00x !
b0x00x00x -
b1001001 5
1%
b10010001111111111111110101010 &
b10010001111111111111110101010 .
#8600
0%
#8700
b0x00x000 !
b0x00x000 -
b1001000 5
1%
#8800
0%
#8900
b0x000xxx !
b0x000xxx -
b1000111 5
1%
#9000
b10010001111111111111110101010 $
b10010001111111111111110101010 /
b10010001111111111111110101010 6
0%
1'
#9100
b0x000xx0 !
b0x000xx0 -
b1000110 5
1%
#9200
0%
#9300
b0x000x0x !
b0x000x0x -
b1000101 5
1%
#9400
0%
#9500
b0x000x00 !
b0x000x00 -
b1000100 5
1%
0'
#9600
0%
#9700
b0x0000xx !
b0x0000xx -
b1000011 5
1%
#9800
0%
#9900
b0x0000x0 !
b0x0000x0 -
b1000010 5
1%
#10000
b11010110000 4
0%
b110101110100000 )
b110101110100000 1
#10100
b0x00000x !
b0x00000x -
b1000001 5
1%
#10200
0%
#10300
b0x000000 !
b0x000000 -
b1000000 5
1%
#10400
0%
#10500
b0 "
b0 3
b0 9
b0xxxxxx !
b0xxxxxx -
b111111 5
1%
1+
#10600
0%
#10700
b0xxxxx0 !
b0xxxxx0 -
b111110 5
1%
#10800
0%
#10900
b0xxxx0x !
b0xxxx0x -
b111101 5
1%
#11000
0%
0+
#11100
b0xxxx00 !
b0xxxx00 -
b111100 5
1%
#11200
0%
#11300
b0xxx0xx !
b0xxx0xx -
b111011 5
1%
#11400
0%
#11500
b0xxx0x0 !
b0xxx0x0 -
b111010 5
1%
#11600
0%
#11700
b0xxx00x !
b0xxx00x -
b111001 5
1%
#11800
0%
#11900
b0xxx000 !
b0xxx000 -
b111000 5
1%
#12000
0%
1'
#12100
b0xx0xxx !
b0xx0xxx -
b110111 5
1%
#12200
0%
#12300
b0xx0xx0 !
b0xx0xx0 -
b110110 5
1%
#12400
0%
#12500
b0xx0x0x !
b0xx0x0x -
b110101 5
1%
0'
#12600
0%
#12700
b0xx0x00 !
b0xx0x00 -
b110100 5
1%
#12800
0%
#12900
b0xx00xx !
b0xx00xx -
b110011 5
1%
#13000
b110110110000 4
0%
b1101101100010000 )
b1101101100010000 1
#13100
b0xx00x0 !
b0xx00x0 -
b110010 5
1%
#13200
0%
#13300
b0xx000x !
b0xx000x -
b110001 5
1%
#13400
0%
#13500
b0 "
b0 3
b0 9
b0xx0000 !
b0xx0000 -
b110000 5
1%
1+
#13600
0%
#13700
b0x0xxxx !
b0x0xxxx -
b101111 5
1%
#13800
0%
#13900
b0x0xxx0 !
b0x0xxx0 -
b101110 5
1%
#14000
0%
0+
#14100
b0x0xx0x !
b0x0xx0x -
b101101 5
1%
#14200
0%
#14300
b0x0xx00 !
b0x0xx00 -
b101100 5
1%
#14400
0%
#14500
b0x0x0xx !
b0x0x0xx -
b101011 5
1%
#14600
0%
#14700
b0x0x0x0 !
b0x0x0x0 -
b101010 5
1%
#14800
0%
#14900
b0x0x00x !
b0x0x00x -
b101001 5
1%
#15000
0%
1'
#15100
b0x0x000 !
b0x0x000 -
b101000 5
1%
#15200
0%
#15300
b0x00xxx !
b0x00xxx -
b100111 5
1%
#15400
0%
#15500
b0x00xx0 !
b0x00xx0 -
b100110 5
1%
0'
#15600
0%
#15700
b0x00x0x !
b0x00x0x -
b100101 5
1%
#15800
0%
#15900
b0x00x00 !
b0x00x00 -
b100100 5
1%
#16000
b111111111111 4
0%
b1111111111111111 )
b1111111111111111 1
#16100
b0x000xx !
b0x000xx -
b100011 5
1%
#16200
0%
#16300
b0x000x0 !
b0x000x0 -
b100010 5
1%
#16400
0%
#16500
b0x0000x !
b0x0000x -
b100001 5
1%
1+
#16600
0%
#16700
b0x00000 !
b0x00000 -
b100000 5
1%
#16800
0%
#16900
b0xxxxx !
b0xxxxx -
b11111 5
1%
#17000
0%
0+
#17100
b0xxxx0 !
b0xxxx0 -
b11110 5
1%
#17200
0%
#17300
b0xxx0x !
b0xxx0x -
b11101 5
1%
#17400
0%
#17500
b0 $
b0 /
b0 6
b0x00xxx0 !
b0x00xxx0 -
b1001110 5
1%
0(
#17600
0%
#17700
b0x00xx0x !
b0x00xx0x -
b1001101 5
1%
#17800
0%
#17900
b0x00xx00 !
b0x00xx00 -
b1001100 5
1%
#18000
0%
1(
#18100
b0x00x0xx !
b0x00x0xx -
b1001011 5
1%
#18200
0%
#18300
b0x00x0x0 !
b0x00x0x0 -
b1001010 5
1%
#18400
0%
#18500
b0x00x00x !
b0x00x00x -
b1001001 5
1%
#18600
0%
#18700
b0x00x000 !
b0x00x000 -
b1001000 5
1%
#18800
0%
#18900
b0x000xxx !
b0x000xxx -
b1000111 5
1%
#19000
0%
#19100
b0x000xx0 !
b0x000xx0 -
b1000110 5
1%
#19200
0%
#19300
b0x000x0x !
b0x000x0x -
b1000101 5
1%
#19400
0%
#19500
b0x000x00 !
b0x000x00 -
b1000100 5
1%
#19600
0%
#19700
b0x0000xx !
b0x0000xx -
b1000011 5
1%
#19800
0%
#19900
b0x0000x0 !
b0x0000x0 -
b1000010 5
1%
#20000
0%
#20100
b0x00000x !
b0x00000x -
b1000001 5
1%
#20200
0%
#20300
b0x000000 !
b0x000000 -
b1000000 5
1%
#20400
0%
#20500
b0xxxxxx !
b0xxxxxx -
b111111 5
1%
#20600
0%
#20700
b0xxxxx0 !
b0xxxxx0 -
b111110 5
1%
#20800
0%
#20900
b0xxxx0x !
b0xxxx0x -
b111101 5
1%
#21000
0%
#21100
b0xxxx00 !
b0xxxx00 -
b111100 5
1%
#21200
0%
#21300
b0xxx0xx !
b0xxx0xx -
b111011 5
1%
#21400
0%
#21500
b0xxx0x0 !
b0xxx0x0 -
b111010 5
1%
#21600
0%
#21700
b0xxx00x !
b0xxx00x -
b111001 5
1%
#21800
0%
#21900
b0xxx000 !
b0xxx000 -
b111000 5
1%
#22000
0%
#22100
b0xx0xxx !
b0xx0xxx -
b110111 5
1%
#22200
0%
#22300
b0xx0xx0 !
b0xx0xx0 -
b110110 5
1%
#22400
0%
#22500
b0xx0x0x !
b0xx0x0x -
b110101 5
1%
#22600
0%
#22700
b0xx0x00 !
b0xx0x00 -
b110100 5
1%
#22800
0%
#22900
b0xx00xx !
b0xx00xx -
b110011 5
1%
#23000
0%
#23100
b0xx00x0 !
b0xx00x0 -
b110010 5
1%
#23200
0%
#23300
b0xx000x !
b0xx000x -
b110001 5
1%
#23400
0%
#23500
b0xx0000 !
b0xx0000 -
b110000 5
1%
#23600
0%
#23700
b0x0xxxx !
b0x0xxxx -
b101111 5
1%
#23800
0%
#23900
b0x0xxx0 !
b0x0xxx0 -
b101110 5
1%
#24000
0%
#24100
b0x0xx0x !
b0x0xx0x -
b101101 5
1%
#24200
0%
#24300
b0x0xx00 !
b0x0xx00 -
b101100 5
1%
#24400
0%
#24500
b0x0x0xx !
b0x0x0xx -
b101011 5
1%
#24600
0%
#24700
b0x0x0x0 !
b0x0x0x0 -
b101010 5
1%
#24800
0%
#24900
b0x0x00x !
b0x0x00x -
b101001 5
1%
#25000
0%
#25100
b0x0x000 !
b0x0x000 -
b101000 5
1%
#25200
0%
#25300
b0x00xxx !
b0x00xxx -
b100111 5
1%
#25400
0%
#25500
b0x00xx0 !
b0x00xx0 -
b100110 5
1%
#25600
0%
#25700
b0x00x0x !
b0x00x0x -
b100101 5
1%
#25800
0%
#25900
b0x00x00 !
b0x00x00 -
b100100 5
1%
#26000
0%
#26100
b0x000xx !
b0x000xx -
b100011 5
1%
#26200
0%
#26300
b0x000x0 !
b0x000x0 -
b100010 5
1%
#26400
0%
#26500
b0x0000x !
b0x0000x -
b100001 5
1%
#26600
0%
#26700
b0x00000 !
b0x00000 -
b100000 5
1%
#26800
0%
#26900
b0xxxxx !
b0xxxxx -
b11111 5
1%
#27000
0%
#27100
b0xxxx0 !
b0xxxx0 -
b11110 5
1%
#27200
0%
#27300
b0xxx0x !
b0xxx0x -
b11101 5
1%
#27400
0%
#27500
b0xxx00 !
b0xxx00 -
b11100 5
1%
#27600
0%
#27700
b0xx0xx !
b0xx0xx -
b11011 5
1%
#27800
0%
#27900
b0xx0x0 !
b0xx0x0 -
b11010 5
1%
#28000
0%
#28100
b0xx00x !
b0xx00x -
b11001 5
1%
#28200
0%
#28300
b0xx000 !
b0xx000 -
b11000 5
1%
#28400
0%
#28500
b0x0xxx !
b0x0xxx -
b10111 5
1%
#28600
0%
#28700
b0x0xx0 !
b0x0xx0 -
b10110 5
1%
#28800
0%
#28900
b0x0x0x !
b0x0x0x -
b10101 5
1%
#29000
0%
#29100
b0x0x00 !
b0x0x00 -
b10100 5
1%
#29200
0%
#29300
b0x00xx !
b0x00xx -
b10011 5
1%
#29400
0%
#29500
b0x00x0 !
b0x00x0 -
b10010 5
1%
#29600
0%
#29700
b0x000x !
b0x000x -
b10001 5
1%
#29800
0%
#29900
b0x0000 !
b0x0000 -
b10000 5
1%
#30000
0%
#30100
b0xxxx !
b0xxxx -
b1111 5
1%
#30200
0%
#30300
b0xxx0 !
b0xxx0 -
b1110 5
1%
#30400
0%
#30500
b0xx0x !
b0xx0x -
b1101 5
1%
#30600
0%
#30700
b0xx00 !
b0xx00 -
b1100 5
1%
#30800
0%
#30900
b0x0xx !
b0x0xx -
b1011 5
1%
#31000
0%
#31100
b0x0x0 !
b0x0x0 -
b1010 5
1%
#31200
0%
#31300
b0x00x !
b0x00x -
b1001 5
1%
#31400
0%
#31500
b0x000 !
b0x000 -
b1000 5
1%
#31600
0%
#31700
b0xxx !
b0xxx -
b111 5
1%
#31800
0%
#31900
b0xx0 !
b0xx0 -
b110 5
1%
#32000
0%
#32100
b0x0x !
b0x0x -
b101 5
1%
#32200
0%
#32300
b0x00 !
b0x00 -
b100 5
1%
#32400
0%
#32500
b0xx !
b0xx -
b11 5
1%
#32600
0%
#32700
b0x0 !
b0x0 -
b10 5
1%
#32800
0%
#32900
b0x !
b0x -
b1 5
1%
#33000
0%
#33100
b0 !
b0 -
b0 5
1%
#33200
0%
#33300
bx !
bx -
b11111111 5
1%
#33400
0%
#33500
bx0 !
bx0 -
b11111110 5
1%
#33600
0%
#33700
bx0x !
bx0x -
b11111101 5
1%
#33800
0%
#33900
bx00 !
bx00 -
b11111100 5
1%
#34000
0%
#34100
bx0xx !
bx0xx -
b11111011 5
1%
#34200
0%
#34300
bx0x0 !
bx0x0 -
b11111010 5
1%
#34400
0%
#34500
bx00x !
bx00x -
b11111001 5
1%
#34600
0%
#34700
bx000 !
bx000 -
b11111000 5
1%
#34800
0%
#34900
bx0xxx !
bx0xxx -
b11110111 5
1%
#35000
0%
#35100
bx0xx0 !
bx0xx0 -
b11110110 5
1%
#35200
0%
#35300
bx0x0x !
bx0x0x -
b11110101 5
1%
#35400
0%
#35500
bx0x00 !
bx0x00 -
b11110100 5
1%
#35600
0%
#35700
bx00xx !
bx00xx -
b11110011 5
1%
#35800
0%
#35900
bx00x0 !
bx00x0 -
b11110010 5
1%
#36000
0%
#36100
bx000x !
bx000x -
b11110001 5
1%
#36200
0%
#36300
bx0000 !
bx0000 -
b11110000 5
1%
#36400
0%
#36500
bx0xxxx !
bx0xxxx -
b11101111 5
1%
#36600
0%
#36700
bx0xxx0 !
bx0xxx0 -
b11101110 5
1%
#36800
0%
#36900
bx0xx0x !
bx0xx0x -
b11101101 5
1%
#37000
0%
#37100
bx0xx00 !
bx0xx00 -
b11101100 5
1%
#37200
0%
#37300
bx0x0xx !
bx0x0xx -
b11101011 5
1%
#37400
0%
#37500
bx0x0x0 !
bx0x0x0 -
b11101010 5
1%
#37600
0%
#37700
bx0x00x !
bx0x00x -
b11101001 5
1%
#37800
0%
#37900
bx0x000 !
bx0x000 -
b11101000 5
1%
#38000
0%
#38100
bx00xxx !
bx00xxx -
b11100111 5
1%
#38200
0%
#38300
bx00xx0 !
bx00xx0 -
b11100110 5
1%
#38400
0%
#38500
bx00x0x !
bx00x0x -
b11100101 5
1%
#38600
0%
#38700
bx00x00 !
bx00x00 -
b11100100 5
1%
#38800
0%
#38900
bx000xx !
bx000xx -
b11100011 5
1%
#39000
0%
#39100
bx000x0 !
bx000x0 -
b11100010 5
1%
#39200
0%
#39300
bx0000x !
bx0000x -
b11100001 5
1%
#39400
0%
#39500
bx00000 !
bx00000 -
b11100000 5
1%
#39600
0%
#39700
bx0xxxxx !
bx0xxxxx -
b11011111 5
1%
#39800
0%
#39900
bx0xxxx0 !
bx0xxxx0 -
b11011110 5
1%
#40000
0%
#40100
bx0xxx0x !
bx0xxx0x -
b11011101 5
1%
#40200
0%
#40300
bx0xxx00 !
bx0xxx00 -
b11011100 5
1%
#40400
0%
#40500
bx0xx0xx !
bx0xx0xx -
b11011011 5
1%
#40600
0%
#40700
bx0xx0x0 !
bx0xx0x0 -
b11011010 5
1%
#40800
0%
#40900
bx0xx00x !
bx0xx00x -
b11011001 5
1%
#41000
0%
#41100
bx0xx000 !
bx0xx000 -
b11011000 5
1%
#41200
0%
#41300
bx0x0xxx !
bx0x0xxx -
b11010111 5
1%
#41400
0%
#41500
bx0x0xx0 !
bx0x0xx0 -
b11010110 5
1%
#41600
0%
#41700
bx0x0x0x !
bx0x0x0x -
b11010101 5
1%
#41800
0%
#41900
bx0x0x00 !
bx0x0x00 -
b11010100 5
1%
#42000
0%
#42100
bx0x00xx !
bx0x00xx -
b11010011 5
1%
#42200
0%
#42300
bx0x00x0 !
bx0x00x0 -
b11010010 5
1%
#42400
0%
#42500
bx0x000x !
bx0x000x -
b11010001 5
1%
#42600
0%
#42700
bx0x0000 !
bx0x0000 -
b11010000 5
1%
#42800
0%
#42900
bx00xxxx !
bx00xxxx -
b11001111 5
1%
#43000
0%
#43100
bx00xxx0 !
bx00xxx0 -
b11001110 5
1%
#43200
0%
#43300
bx00xx0x !
bx00xx0x -
b11001101 5
1%
#43400
0%
#43500
bx00xx00 !
bx00xx00 -
b11001100 5
1%
#43600
0%
#43700
bx00x0xx !
bx00x0xx -
b11001011 5
1%
#43800
0%
#43900
bx00x0x0 !
bx00x0x0 -
b11001010 5
1%
#44000
0%
#44100
bx00x00x !
bx00x00x -
b11001001 5
1%
#44200
0%
#44300
bx00x000 !
bx00x000 -
b11001000 5
1%
#44400
0%
#44500
bx000xxx !
bx000xxx -
b11000111 5
1%
#44600
0%
#44700
bx000xx0 !
bx000xx0 -
b11000110 5
1%
#44800
0%
#44900
bx000x0x !
bx000x0x -
b11000101 5
1%
#45000
0%
#45100
bx000x00 !
bx000x00 -
b11000100 5
1%
#45200
0%
#45300
bx0000xx !
bx0000xx -
b11000011 5
1%
#45400
0%
#45500
bx0000x0 !
bx0000x0 -
b11000010 5
1%
#45600
0%
#45700
bx00000x !
bx00000x -
b11000001 5
1%
#45800
0%
#45900
bx000000 !
bx000000 -
b11000000 5
1%
#46000
0%
#46100
bx0xxxxxx !
bx0xxxxxx -
b10111111 5
1%
#46200
0%
#46300
bx0xxxxx0 !
bx0xxxxx0 -
b10111110 5
1%
#46400
0%
#46500
bx0xxxx0x !
bx0xxxx0x -
b10111101 5
1%
#46600
0%
#46700
bx0xxxx00 !
bx0xxxx00 -
b10111100 5
1%
#46800
0%
#46900
bx0xxx0xx !
bx0xxx0xx -
b10111011 5
1%
#47000
0%
#47100
bx0xxx0x0 !
bx0xxx0x0 -
b10111010 5
1%
#47200
0%
#47300
bx0xxx00x !
bx0xxx00x -
b10111001 5
1%
#47400
0%
#47500
bx0xxx000 !
bx0xxx000 -
b10111000 5
1%
#47600
0%
#47700
bx0xx0xxx !
bx0xx0xxx -
b10110111 5
1%
#47800
0%
#47900
bx0xx0xx0 !
bx0xx0xx0 -
b10110110 5
1%
#48000
0%
1+
#48100
bx0xx0x0x !
bx0xx0x0x -
b10110101 5
1%
#48200
0%
#48300
bx0xx0x00 !
bx0xx0x00 -
b10110100 5
1%
#48400
0%
#48500
bx0xx00xx !
bx0xx00xx -
b10110011 5
1%
#48600
0%
#48700
bx0xx00x0 !
bx0xx00x0 -
b10110010 5
1%
#48800
0%
#48900
bx0xx000x !
bx0xx000x -
b10110001 5
1%
#49000
0%
#49100
bx0xx0000 !
bx0xx0000 -
b10110000 5
1%
#49200
0%
#49300
bx0x0xxxx !
bx0x0xxxx -
b10101111 5
1%
#49400
0%
#49500
bx0x0xxx0 !
bx0x0xxx0 -
b10101110 5
1%
#49600
0%
#49700
bx0x0xx0x !
bx0x0xx0x -
b10101101 5
1%
#49800
0%
#49900
bx0x0xx00 !
bx0x0xx00 -
b10101100 5
1%
#50000
0%
#50100
bx0x0x0xx !
bx0x0x0xx -
b10101011 5
1%
#50200
0%
#50300
bx0x0x0x0 !
bx0x0x0x0 -
b10101010 5
1%
#50400
0%
#50500
bx0x0x00x !
bx0x0x00x -
b10101001 5
1%
#50600
0%
#50700
bx0x0x000 !
bx0x0x000 -
b10101000 5
1%
#50800
0%
#50900
bx0x00xxx !
bx0x00xxx -
b10100111 5
1%
#51000
0%
#51100
bx0x00xx0 !
bx0x00xx0 -
b10100110 5
1%
#51200
0%
#51300
bx0x00x0x !
bx0x00x0x -
b10100101 5
1%
#51400
0%
#51500
bx0x00x00 !
bx0x00x00 -
b10100100 5
1%
#51600
0%
#51700
bx0x000xx !
bx0x000xx -
b10100011 5
1%
#51800
0%
#51900
bx0x000x0 !
bx0x000x0 -
b10100010 5
1%
#52000
0%
#52100
bx0x0000x !
bx0x0000x -
b10100001 5
1%
#52200
0%
#52300
bx0x00000 !
bx0x00000 -
b10100000 5
1%
#52400
0%
#52500
bx00xxxxx !
bx00xxxxx -
b10011111 5
1%
#52600
0%
#52700
bx00xxxx0 !
bx00xxxx0 -
b10011110 5
1%
#52800
0%
#52900
bx00xxx0x !
bx00xxx0x -
b10011101 5
1%
#53000
0%
#53100
bx00xxx00 !
bx00xxx00 -
b10011100 5
1%
#53200
0%
#53300
bx00xx0xx !
bx00xx0xx -
b10011011 5
1%
#53400
0%
#53500
bx00xx0x0 !
bx00xx0x0 -
b10011010 5
1%
#53600
0%
#53700
bx00xx00x !
bx00xx00x -
b10011001 5
1%
#53800
0%
#53900
bx00xx000 !
bx00xx000 -
b10011000 5
1%
#54000
0%
#54100
bx00x0xxx !
bx00x0xxx -
b10010111 5
1%
#54200
0%
#54300
bx00x0xx0 !
bx00x0xx0 -
b10010110 5
1%
#54400
0%
#54500
bx00x0x0x !
bx00x0x0x -
b10010101 5
1%
#54600
0%
#54700
bx00x0x00 !
bx00x0x00 -
b10010100 5
1%
#54800
0%
#54900
bx00x00xx !
bx00x00xx -
b10010011 5
1%
#55000
0%
#55100
bx00x00x0 !
bx00x00x0 -
b10010010 5
1%
#55200
0%
#55300
bx00x000x !
bx00x000x -
b10010001 5
1%
#55400
0%
#55500
bx00x0000 !
bx00x0000 -
b10010000 5
1%
#55600
0%
#55700
bx000xxxx !
bx000xxxx -
b10001111 5
1%
#55800
0%
#55900
bx000xxx0 !
bx000xxx0 -
b10001110 5
1%
#56000
0%
#56100
bx000xx0x !
bx000xx0x -
b10001101 5
1%
#56200
0%
#56300
bx000xx00 !
bx000xx00 -
b10001100 5
1%
#56400
0%
#56500
bx000x0xx !
bx000x0xx -
b10001011 5
1%
#56600
0%
#56700
bx000x0x0 !
bx000x0x0 -
b10001010 5
1%
#56800
0%
#56900
bx000x00x !
bx000x00x -
b10001001 5
1%
#57000
0%
#57100
bx000x000 !
bx000x000 -
b10001000 5
1%
#57200
0%
#57300
bx0000xxx !
bx0000xxx -
b10000111 5
1%
#57400
0%
#57500
bx0000xx0 !
bx0000xx0 -
b10000110 5
1%
#57600
0%
#57700
bx0000x0x !
bx0000x0x -
b10000101 5
1%
#57800
0%
#57900
bx0000x00 !
bx0000x00 -
b10000100 5
1%
#58000
0%
#58100
bx00000xx !
bx00000xx -
b10000011 5
1%
#58200
0%
#58300
bx00000x0 !
bx00000x0 -
b10000010 5
1%
#58400
0%
#58500
bx000000x !
bx000000x -
b10000001 5
1%
#58600
0%
#58700
bx0000000 !
bx0000000 -
b10000000 5
1%
#58800
0%
#58900
b0xxxxxxx !
b0xxxxxxx -
b1111111 5
1%
#59000
0%
#59100
b0xxxxxx0 !
b0xxxxxx0 -
b1111110 5
1%
#59200
0%
#59300
b0xxxxx0x !
b0xxxxx0x -
b1111101 5
1%
#59400
0%
#59500
b0xxxxx00 !
b0xxxxx00 -
b1111100 5
1%
#59600
0%
#59700
b0xxxx0xx !
b0xxxx0xx -
b1111011 5
1%
#59800
0%
#59900
b0xxxx0x0 !
b0xxxx0x0 -
b1111010 5
1%
#60000
0%
